{"mergeCondition":null,"minFlagCol":null,"format":"delta","path":"dbfs:/mnt/fivetran/sap_adls/sap_adls_data_21may_saphanadb/mara/","mergeTargetAlias":"target","overwriteSchema":null,"flagValue":"integer","versionAsOf":null,"writeMode":null,"description":"","replaceWhere":null,"historicColumns":[],"mergeSourceAlias":"source","notMatchedTable":[],"fromTimeCol":null,"notMatchedCondition":null,"matchedTable":[],"notMatchedAction":"insert","partitionColumns":null,"schema":{"type":"struct","fields":[{"name":"mandt","type":"string","nullable":true,"metadata":{"description":"","mappings":[],"tags":[]}},{"name":"matnr","type":"string","nullable":true,"metadata":{"description":"","mappings":[],"tags":[]}},{"name":"etiar","type":"string","nullable":true,"metadata":{"description":"","mappings":[],"tags":[]}},{"name":"_vso_r_pal_ovr_d","type":"decimal(38,10)","nullable":true,"metadata":{"description":"","mappings":[],"tags":[]}},{"name":"cmrel","type":"string","nullable":true,"metadata":{"description":"","mappings":[],"tags":[]}},{"name":"maxdim_uom","type":"string","nullable":true,"metadata":{"description":"","mappings":[],"tags":[]}},{"name":"_sapmp_brad","type":"decimal(38,10)","nullable":true,"metadata":{"description":"","mappings":[],"tags":[]}},{"name":"_cwm_tolgr","type":"string","nullable":true,"metadata":{"description":"","mappings":[],"tags":[]}},{"name":"mfrgr","type":"string","nullable":true,"metadata":{"description":"","mappings":[],"tags":[]}},{"name":"gtin_variant","type":"string","nullable":true,"metadata":{"description":"","mappings":[],"tags":[]}},{"name":"bridge_max_slope","type":"decimal(38,10)","nullable":true,"metadata":{"description":"","mappings":[],"tags":[]}},{"name":"ihivi","type":"string","nullable":true,"metadata":{"description":"","mappings":[],"tags":[]}},{"name":"vpsta","type":"string","nullable":true,"metadata":{"description":"","mappings":[],"tags":[]}},{"name":"ric_id","type":"long","nullable":true,"metadata":{"description":"","mappings":[],"tags":[]}},{"name":"size2","type":"string","nullable":true,"metadata":{"description":"","mappings":[],"tags":[]}},{"name":"rmatp_pb","type":"string","nullable":true,"metadata":{"description":"","mappings":[],"tags":[]}},{"name":"satnr","type":"string","nullable":true,"metadata":{"description":"","mappings":[],"tags":[]}},{"name":"pstat","type":"string","nullable":true,"metadata":{"description":"","mappings":[],"tags":[]}},{"name":"gennr","type":"string","nullable":true,"metadata":{"description":"","mappings":[],"tags":[]}},{"name":"mtpos_mara","type":"string","nullable":true,"metadata":{"description":"","mappings":[],"tags":[]}},{"name":"ntgew","type":"decimal(38,10)","nullable":true,"metadata":{"description":"","mappings":[],"tags":[]}},{"name":"ean11","type":"string","nullable":true,"metadata":{"description":"","mappings":[],"tags":[]}},{"name":"care_code","type":"string","nullable":true,"metadata":{"description":"","mappings":[],"tags":[]}},{"name":"psm_code","type":"string","nullable":true,"metadata":{"description":"","mappings":[],"tags":[]}},{"name":"blanz","type":"string","nullable":true,"metadata":{"description":"","mappings":[],"tags":[]}},{"name":"textile_comp_ind","type":"string","nullable":true,"metadata":{"description":"","mappings":[],"tags":[]}},{"name":"mprof","type":"string","nullable":true,"metadata":{"description":"","mappings":[],"tags":[]}},{"name":"kosch","type":"string","nullable":true,"metadata":{"description":"","mappings":[],"tags":[]}},{"name":"_cwm_xcwmat","type":"string","nullable":true,"metadata":{"description":"","mappings":[],"tags":[]}},{"name":"_vso_r_pal_min_h","type":"decimal(38,10)","nullable":true,"metadata":{"description":"","mappings":[],"tags":[]}},{"name":"magrv","type":"string","nullable":true,"metadata":{"description":"","mappings":[],"tags":[]}},{"name":"maxb","type":"decimal(38,10)","nullable":true,"metadata":{"description":"","mappings":[],"tags":[]}},{"name":"_sapmp_trad","type":"decimal(38,10)","nullable":true,"metadata":{"description":"","mappings":[],"tags":[]}},{"name":"hazmat","type":"string","nullable":true,"metadata":{"description":"","mappings":[],"tags":[]}},{"name":"datab","type":"string","nullable":true,"metadata":{"description":"","mappings":[],"tags":[]}},{"name":"_sttpec_synctime","type":"decimal(38,10)","nullable":true,"metadata":{"description":"","mappings":[],"tags":[]}},{"name":"fashgrd","type":"string","nullable":true,"metadata":{"description":"","mappings":[],"tags":[]}},{"name":"raube","type":"string","nullable":true,"metadata":{"description":"","mappings":[],"tags":[]}},{"name":"vabme","type":"string","nullable":true,"metadata":{"description":"","mappings":[],"tags":[]}},{"name":"_sapmp_fbak","type":"string","nullable":true,"metadata":{"description":"","mappings":[],"tags":[]}},{"name":"cadkz","type":"string","nullable":true,"metadata":{"description":"","mappings":[],"tags":[]}},{"name":"zzmatnr","type":"string","nullable":true,"metadata":{"description":"","mappings":[],"tags":[]}},{"name":"zeivr","type":"string","nullable":true,"metadata":{"description":"","mappings":[],"tags":[]}},{"name":"lvorm","type":"string","nullable":true,"metadata":{"description":"","mappings":[],"tags":[]}},{"name":"free_char","type":"string","nullable":true,"metadata":{"description":"","mappings":[],"tags":[]}},{"name":"ernam","type":"string","nullable":true,"metadata":{"description":"","mappings":[],"tags":[]}},{"name":"fsh_sc_mid","type":"string","nullable":true,"metadata":{"description":"","mappings":[],"tags":[]}},{"name":"herkl","type":"string","nullable":true,"metadata":{"description":"","mappings":[],"tags":[]}},{"name":"fiber_part4","type":"string","nullable":true,"metadata":{"description":"","mappings":[],"tags":[]}},{"name":"nsnid","type":"string","nullable":true,"metadata":{"description":"","mappings":[],"tags":[]}},{"name":"cuobf","type":"string","nullable":true,"metadata":{"description":"","mappings":[],"tags":[]}},{"name":"zeiar","type":"string","nullable":true,"metadata":{"description":"","mappings":[],"tags":[]}},{"name":"volto","type":"decimal(38,10)","nullable":true,"metadata":{"description":"","mappings":[],"tags":[]}},{"name":"prdha","type":"string","nullable":true,"metadata":{"description":"","mappings":[],"tags":[]}},{"name":"_bev1_nestruccat","type":"string","nullable":true,"metadata":{"description":"","mappings":[],"tags":[]}},{"name":"created_at_time","type":"string","nullable":true,"metadata":{"description":"","mappings":[],"tags":[]}},{"name":"ekwsl","type":"string","nullable":true,"metadata":{"description":"","mappings":[],"tags":[]}},{"name":"bwscl","type":"string","nullable":true,"metadata":{"description":"","mappings":[],"tags":[]}},{"name":"kzkfg","type":"string","nullable":true,"metadata":{"description":"","mappings":[],"tags":[]}},{"name":"mbrsh","type":"string","nullable":true,"metadata":{"description":"","mappings":[],"tags":[]}},{"name":"srv_dura","type":"decimal(38,10)","nullable":true,"metadata":{"description":"","mappings":[],"tags":[]}},{"name":"cwqproc","type":"string","nullable":true,"metadata":{"description":"","mappings":[],"tags":[]}},{"name":"stfak","type":"integer","nullable":true,"metadata":{"description":"","mappings":[],"tags":[]}},{"name":"kzkup","type":"string","nullable":true,"metadata":{"description":"","mappings":[],"tags":[]}},{"name":"kznfm","type":"string","nullable":true,"metadata":{"description":"","mappings":[],"tags":[]}},{"name":"kzrev","type":"string","nullable":true,"metadata":{"description":"","mappings":[],"tags":[]}},{"name":"_sttpec_sertype","type":"integer","nullable":true,"metadata":{"description":"","mappings":[],"tags":[]}},{"name":"sprof","type":"string","nullable":true,"metadata":{"description":"","mappings":[],"tags":[]}},{"name":"vpreh","type":"decimal(38,10)","nullable":true,"metadata":{"description":"","mappings":[],"tags":[]}},{"name":"ersda","type":"string","nullable":true,"metadata":{"description":"","mappings":[],"tags":[]}},{"name":"matnr_external","type":"string","nullable":true,"metadata":{"description":"","mappings":[],"tags":[]}},{"name":"qmpur","type":"string","nullable":true,"metadata":{"description":"","mappings":[],"tags":[]}},{"name":"zeifo","type":"string","nullable":true,"metadata":{"description":"","mappings":[],"tags":[]}},{"name":"kzumw","type":"string","nullable":true,"metadata":{"description":"","mappings":[],"tags":[]}},{"name":"bridge_tresh","type":"decimal(38,10)","nullable":true,"metadata":{"description":"","mappings":[],"tags":[]}},{"name":"fsh_mg_at2","type":"string","nullable":true,"metadata":{"description":"","mappings":[],"tags":[]}},{"name":"bstme","type":"string","nullable":true,"metadata":{"description":"","mappings":[],"tags":[]}},{"name":"begru","type":"string","nullable":true,"metadata":{"description":"","mappings":[],"tags":[]}},{"name":"maxc_tol","type":"decimal(38,10)","nullable":true,"metadata":{"description":"","mappings":[],"tags":[]}},{"name":"hndlcode","type":"string","nullable":true,"metadata":{"description":"","mappings":[],"tags":[]}},{"name":"inhme","type":"string","nullable":true,"metadata":{"description":"","mappings":[],"tags":[]}},{"name":"mstae","type":"string","nullable":true,"metadata":{"description":"","mappings":[],"tags":[]}},{"name":"bstat","type":"string","nullable":true,"metadata":{"description":"","mappings":[],"tags":[]}},{"name":"last_changed_time","type":"string","nullable":true,"metadata":{"description":"","mappings":[],"tags":[]}},{"name":"numtp","type":"string","nullable":true,"metadata":{"description":"","mappings":[],"tags":[]}},{"name":"sgt_rel","type":"string","nullable":true,"metadata":{"description":"","mappings":[],"tags":[]}},{"name":"height_nonflat_uom","type":"string","nullable":true,"metadata":{"description":"","mappings":[],"tags":[]}},{"name":"meins","type":"string","nullable":true,"metadata":{"description":"","mappings":[],"tags":[]}},{"name":"msbookpartno","type":"string","nullable":true,"metadata":{"description":"","mappings":[],"tags":[]}},{"name":"allow_pmat_igno","type":"string","nullable":true,"metadata":{"description":"","mappings":[],"tags":[]}},{"name":"fsh_sealv","type":"string","nullable":true,"metadata":{"description":"","mappings":[],"tags":[]}},{"name":"identification_tag_type","type":"string","nullable":true,"metadata":{"description":"","mappings":[],"tags":[]}},{"name":"cmeth","type":"string","nullable":true,"metadata":{"description":"","mappings":[],"tags":[]}},{"name":"_sttpec_syncact","type":"string","nullable":true,"metadata":{"description":"","mappings":[],"tags":[]}},{"name":"saity","type":"string","nullable":true,"metadata":{"description":"","mappings":[],"tags":[]}},{"name":"_cwm_tara","type":"string","nullable":true,"metadata":{"description":"","mappings":[],"tags":[]}},{"name":"ovlpn","type":"string","nullable":true,"metadata":{"description":"","mappings":[],"tags":[]}},{"name":"_dsd_sv_cnt_grp","type":"string","nullable":true,"metadata":{"description":"","mappings":[],"tags":[]}},{"name":"zeinr","type":"string","nullable":true,"metadata":{"description":"","mappings":[],"tags":[]}},{"name":"behvo","type":"string","nullable":true,"metadata":{"description":"","mappings":[],"tags":[]}},{"name":"blatt","type":"string","nullable":true,"metadata":{"description":"","mappings":[],"tags":[]}},{"name":"scm_excl_expedite","type":"string","nullable":true,"metadata":{"description":"","mappings":[],"tags":[]}},{"name":"dpcbt","type":"string","nullable":true,"metadata":{"description":"","mappings":[],"tags":[]}},{"name":"mhdrz","type":"decimal(38,10)","nullable":true,"metadata":{"description":"","mappings":[],"tags":[]}},{"name":"logistical_mat_category","type":"string","nullable":true,"metadata":{"description":"","mappings":[],"tags":[]}},{"name":"sales_material","type":"string","nullable":true,"metadata":{"description":"","mappings":[],"tags":[]}},{"name":"laeng","type":"decimal(38,10)","nullable":true,"metadata":{"description":"","mappings":[],"tags":[]}},{"name":"_sapmp_kedu","type":"decimal(38,10)","nullable":true,"metadata":{"description":"","mappings":[],"tags":[]}},{"name":"tolerance_type","type":"string","nullable":true,"metadata":{"description":"","mappings":[],"tags":[]}},{"name":"fiber_part3","type":"string","nullable":true,"metadata":{"description":"","mappings":[],"tags":[]}},{"name":"maxc","type":"decimal(38,10)","nullable":true,"metadata":{"description":"","mappings":[],"tags":[]}},{"name":"cwqtolgr","type":"string","nullable":true,"metadata":{"description":"","mappings":[],"tags":[]}},{"name":"prod_shape","type":"string","nullable":true,"metadata":{"description":"","mappings":[],"tags":[]}},{"name":"mstdv","type":"string","nullable":true,"metadata":{"description":"","mappings":[],"tags":[]}},{"name":"sgt_scope","type":"string","nullable":true,"metadata":{"description":"","mappings":[],"tags":[]}},{"name":"fuelg","type":"decimal(38,10)","nullable":true,"metadata":{"description":"","mappings":[],"tags":[]}},{"name":"size1","type":"string","nullable":true,"metadata":{"description":"","mappings":[],"tags":[]}},{"name":"pmata","type":"string","nullable":true,"metadata":{"description":"","mappings":[],"tags":[]}},{"name":"ervoe","type":"string","nullable":true,"metadata":{"description":"","mappings":[],"tags":[]}},{"name":"fiber_code5","type":"string","nullable":true,"metadata":{"description":"","mappings":[],"tags":[]}},{"name":"brgew","type":"decimal(38,10)","nullable":true,"metadata":{"description":"","mappings":[],"tags":[]}},{"name":"brand_id","type":"string","nullable":true,"metadata":{"description":"","mappings":[],"tags":[]}},{"name":"formt","type":"string","nullable":true,"metadata":{"description":"","mappings":[],"tags":[]}},{"name":"ferth","type":"string","nullable":true,"metadata":{"description":"","mappings":[],"tags":[]}},{"name":"_vso_r_tilt_ind","type":"string","nullable":true,"metadata":{"description":"","mappings":[],"tags":[]}},{"name":"prd_startdt","type":"string","nullable":true,"metadata":{"description":"","mappings":[],"tags":[]}},{"name":"scm_restrict_invbal","type":"string","nullable":true,"metadata":{"description":"","mappings":[],"tags":[]}},{"name":"sgt_covsa","type":"string","nullable":true,"metadata":{"description":"","mappings":[],"tags":[]}},{"name":"commodity","type":"string","nullable":true,"metadata":{"description":"","mappings":[],"tags":[]}},{"name":"kzgvh","type":"string","nullable":true,"metadata":{"description":"","mappings":[],"tags":[]}},{"name":"scm_matid_guid16","type":"binary","nullable":true,"metadata":{"description":"","mappings":[],"tags":[]}},{"name":"scm_matid_guid22","type":"string","nullable":true,"metadata":{"description":"","mappings":[],"tags":[]}},{"name":"mcond","type":"string","nullable":true,"metadata":{"description":"","mappings":[],"tags":[]}},{"name":"mfrnr","type":"string","nullable":true,"metadata":{"description":"","mappings":[],"tags":[]}},{"name":"_sttpec_country_ref","type":"string","nullable":true,"metadata":{"description":"","mappings":[],"tags":[]}},{"name":"_sapmp_abmein","type":"string","nullable":true,"metadata":{"description":"","mappings":[],"tags":[]}},{"name":"pilferable","type":"string","nullable":true,"metadata":{"description":"","mappings":[],"tags":[]}},{"name":"mtart","type":"string","nullable":true,"metadata":{"description":"","mappings":[],"tags":[]}},{"name":"packcode","type":"string","nullable":true,"metadata":{"description":"","mappings":[],"tags":[]}},{"name":"_vso_r_pal_b_ht","type":"decimal(38,10)","nullable":true,"metadata":{"description":"","mappings":[],"tags":[]}},{"name":"medium","type":"string","nullable":true,"metadata":{"description":"","mappings":[],"tags":[]}},{"name":"gds_relevant","type":"string","nullable":true,"metadata":{"description":"","mappings":[],"tags":[]}},{"name":"mhdhb","type":"decimal(38,10)","nullable":true,"metadata":{"description":"","mappings":[],"tags":[]}},{"name":"aeklk","type":"string","nullable":true,"metadata":{"description":"","mappings":[],"tags":[]}},{"name":"sled_bbd","type":"string","nullable":true,"metadata":{"description":"","mappings":[],"tags":[]}},{"name":"gewto","type":"decimal(38,10)","nullable":true,"metadata":{"description":"","mappings":[],"tags":[]}},{"name":"_vso_r_bot_ind","type":"string","nullable":true,"metadata":{"description":"","mappings":[],"tags":[]}},{"name":"_sapmp_kadp","type":"decimal(38,10)","nullable":true,"metadata":{"description":"","mappings":[],"tags":[]}},{"name":"scm_bod_deplvl","type":"string","nullable":true,"metadata":{"description":"","mappings":[],"tags":[]}},{"name":"inhal","type":"decimal(38,10)","nullable":true,"metadata":{"description":"","mappings":[],"tags":[]}},{"name":"bismt","type":"string","nullable":true,"metadata":{"description":"","mappings":[],"tags":[]}},{"name":"iloos","type":"string","nullable":true,"metadata":{"description":"","mappings":[],"tags":[]}},{"name":"_vso_r_top_ind","type":"string","nullable":true,"metadata":{"description":"","mappings":[],"tags":[]}},{"name":"_vso_r_tol_b_ht","type":"decimal(38,10)","nullable":true,"metadata":{"description":"","mappings":[],"tags":[]}},{"name":"groes","type":"string","nullable":true,"metadata":{"description":"","mappings":[],"tags":[]}},{"name":"labor","type":"string","nullable":true,"metadata":{"description":"","mappings":[],"tags":[]}},{"name":"dummy_prd_incl_eew_ps","type":"string","nullable":true,"metadata":{"description":"","mappings":[],"tags":[]}},{"name":"ergew","type":"decimal(38,10)","nullable":true,"metadata":{"description":"","mappings":[],"tags":[]}},{"name":"mo_profile_id","type":"string","nullable":true,"metadata":{"description":"","mappings":[],"tags":[]}},{"name":"fiber_part2","type":"string","nullable":true,"metadata":{"description":"","mappings":[],"tags":[]}},{"name":"_sapmp_sptr","type":"decimal(38,10)","nullable":true,"metadata":{"description":"","mappings":[],"tags":[]}},{"name":"mhdlp","type":"decimal(38,10)","nullable":true,"metadata":{"description":"","mappings":[],"tags":[]}},{"name":"_sapmp_kadu","type":"decimal(38,10)","nullable":true,"metadata":{"description":"","mappings":[],"tags":[]}},{"name":"loglev_reto","type":"string","nullable":true,"metadata":{"description":"","mappings":[],"tags":[]}},{"name":"adprof","type":"string","nullable":true,"metadata":{"description":"","mappings":[],"tags":[]}},{"name":"bmatn","type":"string","nullable":true,"metadata":{"description":"","mappings":[],"tags":[]}},{"name":"iprkz","type":"string","nullable":true,"metadata":{"description":"","mappings":[],"tags":[]}},{"name":"scm_shlf_lfe_req_max","type":"decimal(38,10)","nullable":true,"metadata":{"description":"","mappings":[],"tags":[]}},{"name":"cwqrel","type":"string","nullable":true,"metadata":{"description":"","mappings":[],"tags":[]}},{"name":"fiber_code4","type":"string","nullable":true,"metadata":{"description":"","mappings":[],"tags":[]}},{"name":"fsh_seaim","type":"string","nullable":true,"metadata":{"description":"","mappings":[],"tags":[]}},{"name":"sgt_stat","type":"string","nullable":true,"metadata":{"description":"","mappings":[],"tags":[]}},{"name":"tempb","type":"string","nullable":true,"metadata":{"description":"","mappings":[],"tags":[]}},{"name":"picnum","type":"string","nullable":true,"metadata":{"description":"","mappings":[],"tags":[]}},{"name":"fsh_mg_at1","type":"string","nullable":true,"metadata":{"description":"","mappings":[],"tags":[]}},{"name":"_cwm_valum","type":"string","nullable":true,"metadata":{"description":"","mappings":[],"tags":[]}},{"name":"kunnr","type":"string","nullable":true,"metadata":{"description":"","mappings":[],"tags":[]}},{"name":"taklv","type":"string","nullable":true,"metadata":{"description":"","mappings":[],"tags":[]}},{"name":"nrfhg","type":"string","nullable":true,"metadata":{"description":"","mappings":[],"tags":[]}},{"name":"attyp","type":"string","nullable":true,"metadata":{"description":"","mappings":[],"tags":[]}},{"name":"spart","type":"string","nullable":true,"metadata":{"description":"","mappings":[],"tags":[]}},{"name":"mfrpn","type":"string","nullable":true,"metadata":{"description":"","mappings":[],"tags":[]}},{"name":"przus","type":"string","nullable":true,"metadata":{"description":"","mappings":[],"tags":[]}},{"name":"entar","type":"string","nullable":true,"metadata":{"description":"","mappings":[],"tags":[]}},{"name":"_sttpec_prdcat","type":"string","nullable":true,"metadata":{"description":"","mappings":[],"tags":[]}},{"name":"saisj","type":"string","nullable":true,"metadata":{"description":"","mappings":[],"tags":[]}},{"name":"kzwsm","type":"string","nullable":true,"metadata":{"description":"","mappings":[],"tags":[]}},{"name":"disst","type":"string","nullable":true,"metadata":{"description":"","mappings":[],"tags":[]}},{"name":"srv_escal","type":"string","nullable":true,"metadata":{"description":"","mappings":[],"tags":[]}},{"name":"_vso_r_kzgvh_ind","type":"string","nullable":true,"metadata":{"description":"","mappings":[],"tags":[]}},{"name":"vhart","type":"string","nullable":true,"metadata":{"description":"","mappings":[],"tags":[]}},{"name":"ipmipproduct","type":"string","nullable":true,"metadata":{"description":"","mappings":[],"tags":[]}},{"name":"whstc","type":"string","nullable":true,"metadata":{"description":"","mappings":[],"tags":[]}},{"name":"meabm","type":"string","nullable":true,"metadata":{"description":"","mappings":[],"tags":[]}},{"name":"_vso_r_quan_unit","type":"string","nullable":true,"metadata":{"description":"","mappings":[],"tags":[]}},{"name":"rdmhd","type":"string","nullable":true,"metadata":{"description":"","mappings":[],"tags":[]}},{"name":"etiag","type":"string","nullable":true,"metadata":{"description":"","mappings":[],"tags":[]}},{"name":"_vso_r_no_p_gvh","type":"string","nullable":true,"metadata":{"description":"","mappings":[],"tags":[]}},{"name":"serlv","type":"string","nullable":true,"metadata":{"description":"","mappings":[],"tags":[]}},{"name":"bwvor","type":"string","nullable":true,"metadata":{"description":"","mappings":[],"tags":[]}},{"name":"qqtimeuom","type":"string","nullable":true,"metadata":{"description":"","mappings":[],"tags":[]}},{"name":"sgt_csgr","type":"string","nullable":true,"metadata":{"description":"","mappings":[],"tags":[]}},{"name":"_sapmp_fbdk","type":"decimal(38,10)","nullable":true,"metadata":{"description":"","mappings":[],"tags":[]}},{"name":"_vso_r_stack_no","type":"string","nullable":true,"metadata":{"description":"","mappings":[],"tags":[]}},{"name":"prd_enddt","type":"string","nullable":true,"metadata":{"description":"","mappings":[],"tags":[]}},{"name":"ps_smartform","type":"string","nullable":true,"metadata":{"description":"","mappings":[],"tags":[]}},{"name":"som_ctr_autorenewal","type":"string","nullable":true,"metadata":{"description":"","mappings":[],"tags":[]}},{"name":"plgtp","type":"string","nullable":true,"metadata":{"description":"","mappings":[],"tags":[]}},{"name":"som_cycle","type":"string","nullable":true,"metadata":{"description":"","mappings":[],"tags":[]}},{"name":"retdelc","type":"string","nullable":true,"metadata":{"description":"","mappings":[],"tags":[]}},{"name":"scm_puom","type":"string","nullable":true,"metadata":{"description":"","mappings":[],"tags":[]}},{"name":"fiber_part1","type":"string","nullable":true,"metadata":{"description":"","mappings":[],"tags":[]}},{"name":"overhang_tresh","type":"decimal(38,10)","nullable":true,"metadata":{"description":"","mappings":[],"tags":[]}},{"name":"stoff","type":"string","nullable":true,"metadata":{"description":"","mappings":[],"tags":[]}},{"name":"_vso_r_pal_ind","type":"string","nullable":true,"metadata":{"description":"","mappings":[],"tags":[]}},{"name":"qqtime","type":"decimal(38,10)","nullable":true,"metadata":{"description":"","mappings":[],"tags":[]}},{"name":"scm_prod_paoopt","type":"string","nullable":true,"metadata":{"description":"","mappings":[],"tags":[]}},{"name":"fiber_code3","type":"string","nullable":true,"metadata":{"description":"","mappings":[],"tags":[]}},{"name":"logunit","type":"string","nullable":true,"metadata":{"description":"","mappings":[],"tags":[]}},{"name":"etifo","type":"string","nullable":true,"metadata":{"description":"","mappings":[],"tags":[]}},{"name":"flagclass","type":"string","nullable":true,"metadata":{"description":"","mappings":[],"tags":[]}},{"name":"rbnrm","type":"string","nullable":true,"metadata":{"description":"","mappings":[],"tags":[]}},{"name":"adspc_spc","type":"string","nullable":true,"metadata":{"description":"","mappings":[],"tags":[]}},{"name":"hutyp","type":"string","nullable":true,"metadata":{"description":"","mappings":[],"tags":[]}},{"name":"scm_kitcomp","type":"string","nullable":true,"metadata":{"description":"","mappings":[],"tags":[]}},{"name":"_bev1_luldegrp","type":"string","nullable":true,"metadata":{"description":"","mappings":[],"tags":[]}},{"name":"gewei","type":"string","nullable":true,"metadata":{"description":"","mappings":[],"tags":[]}},{"name":"breit","type":"decimal(38,10)","nullable":true,"metadata":{"description":"","mappings":[],"tags":[]}},{"name":"inv_pln_mode","type":"string","nullable":true,"metadata":{"description":"","mappings":[],"tags":[]}},{"name":"color","type":"string","nullable":true,"metadata":{"description":"","mappings":[],"tags":[]}},{"name":"animal_origin","type":"string","nullable":true,"metadata":{"description":"","mappings":[],"tags":[]}},{"name":"laeda","type":"string","nullable":true,"metadata":{"description":"","mappings":[],"tags":[]}},{"name":"_vso_r_pal_ovr_w","type":"decimal(38,10)","nullable":true,"metadata":{"description":"","mappings":[],"tags":[]}},{"name":"serial","type":"string","nullable":true,"metadata":{"description":"","mappings":[],"tags":[]}},{"name":"tragr","type":"string","nullable":true,"metadata":{"description":"","mappings":[],"tags":[]}},{"name":"volum","type":"decimal(38,10)","nullable":true,"metadata":{"description":"","mappings":[],"tags":[]}},{"name":"_sapmp_aho","type":"string","nullable":true,"metadata":{"description":"","mappings":[],"tags":[]}},{"name":"_bev1_luleinh","type":"string","nullable":true,"metadata":{"description":"","mappings":[],"tags":[]}},{"name":"compl","type":"string","nullable":true,"metadata":{"description":"","mappings":[],"tags":[]}},{"name":"matfi","type":"string","nullable":true,"metadata":{"description":"","mappings":[],"tags":[]}},{"name":"imatn","type":"string","nullable":true,"metadata":{"description":"","mappings":[],"tags":[]}},{"name":"maxh","type":"decimal(38,10)","nullable":true,"metadata":{"description":"","mappings":[],"tags":[]}},{"name":"scm_maturity_dur","type":"decimal(38,10)","nullable":true,"metadata":{"description":"","mappings":[],"tags":[]}},{"name":"anp","type":"string","nullable":true,"metadata":{"description":"","mappings":[],"tags":[]}},{"name":"hutyp_dflt","type":"string","nullable":true,"metadata":{"description":"","mappings":[],"tags":[]}},{"name":"mstav","type":"string","nullable":true,"metadata":{"description":"","mappings":[],"tags":[]}},{"name":"chml_cmplnc_rlvnce_ind","type":"string","nullable":true,"metadata":{"description":"","mappings":[],"tags":[]}},{"name":"mstde","type":"string","nullable":true,"metadata":{"description":"","mappings":[],"tags":[]}},{"name":"fiber_code2","type":"string","nullable":true,"metadata":{"description":"","mappings":[],"tags":[]}},{"name":"som_tc_schema","type":"string","nullable":true,"metadata":{"description":"","mappings":[],"tags":[]}},{"name":"_sapmp_mifrr","type":"decimal(38,10)","nullable":true,"metadata":{"description":"","mappings":[],"tags":[]}},{"name":"ergei","type":"string","nullable":true,"metadata":{"description":"","mappings":[],"tags":[]}},{"name":"size1_atinn","type":"string","nullable":true,"metadata":{"description":"","mappings":[],"tags":[]}},{"name":"maxl","type":"decimal(38,10)","nullable":true,"metadata":{"description":"","mappings":[],"tags":[]}},{"name":"sdm_version","type":"string","nullable":true,"metadata":{"description":"","mappings":[],"tags":[]}},{"name":"aeszn","type":"string","nullable":true,"metadata":{"description":"","mappings":[],"tags":[]}},{"name":"mlgut","type":"string","nullable":true,"metadata":{"description":"","mappings":[],"tags":[]}},{"name":"tare_var","type":"string","nullable":true,"metadata":{"description":"","mappings":[],"tags":[]}},{"name":"weora","type":"string","nullable":true,"metadata":{"description":"","mappings":[],"tags":[]}},{"name":"dfs_mfrp2","type":"string","nullable":true,"metadata":{"description":"","mappings":[],"tags":[]}},{"name":"size2_atinn","type":"string","nullable":true,"metadata":{"description":"","mappings":[],"tags":[]}},{"name":"hoehe","type":"decimal(38,10)","nullable":true,"metadata":{"description":"","mappings":[],"tags":[]}},{"name":"srv_dura_uom","type":"string","nullable":true,"metadata":{"description":"","mappings":[],"tags":[]}},{"name":"scm_drp_gl_stock","type":"string","nullable":true,"metadata":{"description":"","mappings":[],"tags":[]}},{"name":"_sapmp_rili","type":"string","nullable":true,"metadata":{"description":"","mappings":[],"tags":[]}},{"name":"kzeff","type":"string","nullable":true,"metadata":{"description":"","mappings":[],"tags":[]}},{"name":"inhbr","type":"decimal(38,10)","nullable":true,"metadata":{"description":"","mappings":[],"tags":[]}},{"name":"bflme","type":"string","nullable":true,"metadata":{"description":"","mappings":[],"tags":[]}},{"name":"fsh_mg_at3","type":"string","nullable":true,"metadata":{"description":"","mappings":[],"tags":[]}},{"name":"extwg","type":"string","nullable":true,"metadata":{"description":"","mappings":[],"tags":[]}},{"name":"profl","type":"string","nullable":true,"metadata":{"description":"","mappings":[],"tags":[]}},{"name":"xgrdt","type":"string","nullable":true,"metadata":{"description":"","mappings":[],"tags":[]}},{"name":"saiso","type":"string","nullable":true,"metadata":{"description":"","mappings":[],"tags":[]}},{"name":"_cwm_tarum","type":"string","nullable":true,"metadata":{"description":"","mappings":[],"tags":[]}},{"name":"normt","type":"string","nullable":true,"metadata":{"description":"","mappings":[],"tags":[]}},{"name":"matkl","type":"string","nullable":true,"metadata":{"description":"","mappings":[],"tags":[]}},{"name":"liqdt","type":"string","nullable":true,"metadata":{"description":"","mappings":[],"tags":[]}},{"name":"srv_serwi","type":"string","nullable":true,"metadata":{"description":"","mappings":[],"tags":[]}},{"name":"varid","type":"binary","nullable":true,"metadata":{"description":"","mappings":[],"tags":[]}},{"name":"som_cycle_rule","type":"string","nullable":true,"metadata":{"description":"","mappings":[],"tags":[]}},{"name":"ervol","type":"decimal(38,10)","nullable":true,"metadata":{"description":"","mappings":[],"tags":[]}},{"name":"whmatgr","type":"string","nullable":true,"metadata":{"description":"","mappings":[],"tags":[]}},{"name":"bbtyp","type":"string","nullable":true,"metadata":{"description":"","mappings":[],"tags":[]}},{"name":"height_nonflat","type":"decimal(38,10)","nullable":true,"metadata":{"description":"","mappings":[],"tags":[]}},{"name":"wrkst","type":"string","nullable":true,"metadata":{"description":"","mappings":[],"tags":[]}},{"name":"_dsd_vc_group","type":"string","nullable":true,"metadata":{"description":"","mappings":[],"tags":[]}},{"name":"dfs_sensitivity_key","type":"string","nullable":true,"metadata":{"description":"","mappings":[],"tags":[]}},{"name":"icfa","type":"string","nullable":true,"metadata":{"description":"","mappings":[],"tags":[]}},{"name":"color_atinn","type":"string","nullable":true,"metadata":{"description":"","mappings":[],"tags":[]}},{"name":"_dsd_sl_toltyp","type":"string","nullable":true,"metadata":{"description":"","mappings":[],"tags":[]}},{"name":"_vso_r_stack_ind","type":"string","nullable":true,"metadata":{"description":"","mappings":[],"tags":[]}},{"name":"_sapmp_spbi","type":"decimal(38,10)","nullable":true,"metadata":{"description":"","mappings":[],"tags":[]}},{"name":"_sapmp_fbhk","type":"decimal(38,10)","nullable":true,"metadata":{"description":"","mappings":[],"tags":[]}},{"name":"xchpf","type":"string","nullable":true,"metadata":{"description":"","mappings":[],"tags":[]}},{"name":"eannr","type":"string","nullable":true,"metadata":{"description":"","mappings":[],"tags":[]}},{"name":"qgrp","type":"string","nullable":true,"metadata":{"description":"","mappings":[],"tags":[]}},{"name":"fiber_code1","type":"string","nullable":true,"metadata":{"description":"","mappings":[],"tags":[]}},{"name":"wesch","type":"decimal(38,10)","nullable":true,"metadata":{"description":"","mappings":[],"tags":[]}},{"name":"scm_shlf_lfe_req_min","type":"decimal(38,10)","nullable":true,"metadata":{"description":"","mappings":[],"tags":[]}},{"name":"xgchp","type":"string","nullable":true,"metadata":{"description":"","mappings":[],"tags":[]}},{"name":"productoid","type":"string","nullable":true,"metadata":{"description":"","mappings":[],"tags":[]}},{"name":"rmatp","type":"string","nullable":true,"metadata":{"description":"","mappings":[],"tags":[]}},{"name":"voleh","type":"string","nullable":true,"metadata":{"description":"","mappings":[],"tags":[]}},{"name":"newprod_indi","type":"string","nullable":true,"metadata":{"description":"","mappings":[],"tags":[]}},{"name":"dg_pack_status","type":"string","nullable":true,"metadata":{"description":"","mappings":[],"tags":[]}},{"name":"aenam","type":"string","nullable":true,"metadata":{"description":"","mappings":[],"tags":[]}},{"name":"_sttpec_syncchg","type":"string","nullable":true,"metadata":{"description":"","mappings":[],"tags":[]}},{"name":"fiber_part5","type":"string","nullable":true,"metadata":{"description":"","mappings":[],"tags":[]}},{"name":"_fivetran_deleted","type":"boolean","nullable":true,"metadata":{"description":"","mappings":[],"tags":[]}},{"name":"_fivetran_synced","type":"timestamp","nullable":true,"metadata":{"description":"","mappings":[],"tags":[]}}]},"activeTab":"whenMatched","maxFlagCol":null,"matchedConditionDelete":null,"componentInfo":{"gemId":"gitUri=http://gitserver:3000/DxEheDCJ_team_5751/DxEheDCJ_project_12654.git&subPath=&tag=0.2.12&projectSubscriptionProjectId=12654&path=gems/delta","projectName":"ProphecySparkBasicsPython"},"matchedActionDelete":"ignore","timestampAsOf":null,"mergeSchema":null,"toTimeCol":null,"optimizeWrite":null,"keyColumns":[],"matchedCondition":null,"matchedAction":"update","datasetType":"File"}